Kil0p3/__init__.py
Kil0p3/run.py
Kil0p3/config/__init__.py
Kil0p3/config/constants.py
Kil0p3/config/settings.py
Kil0p3/core/__init__.py
Kil0p3/core/encryption.py
Kil0p3/core/hwid.py
Kil0p3/core/license.py
Kil0p3/core/signature.py
Kil0p3/core/tamper.py
Kil0p3/core/timecheck.py
Kil0p3/core/trial.py
Kil0p3/core/validator.py
Kil0p3/network/__init__.py
Kil0p3/network/api_client.py
Kil0p3/network/firewall.py
Kil0p3/network/ip_check.py
Kil0p3/runtime/__init__.py
Kil0p3/runtime/attempt_counter.py
Kil0p3/runtime/block_state.py
Kil0p3/runtime/self_delete.py
Kil0p3/runtime/watchdog.py
Kil0p3/security/__init__.py
Kil0p3/security/anti_debug.py
Kil0p3/security/obfuscation.py
Kil0p3/security/vm_detect.py
Kil0p3/server/app.py
Kil0p3/server/database.py
Kil0p3/server/api/licenses.py
Kil0p3/server/api/validation.py
Kil0p3/tools/__init__.py
Kil0p3/tools/logger.py
Kil0p3/tools/utils.py
Kil0p3/ui/__init__.py
Kil0p3/ui/auth_window.py
Kil0p3/ui/banned_window.py
Kil0p3/ui/status_window.py
Kil0p3/ui/trial_expired_window.py
kil0p3-1.0.4.dist-info/METADATA
kil0p3-1.0.4.dist-info/WHEEL
kil0p3-1.0.4.dist-info/entry_points.txt
kil0p3-1.0.4.dist-info/top_level.txt
kil0p3-1.0.4.dist-info/RECORD
