Metadata-Version: 2.4
Name: kil0p3
Version: 1.0.4
Summary: Advanced Python Application Protection Library with automatic license validation
Home-page: https://github.com/kil0p3-security/kil0p3
Author: Kil0p3 Security Team
Author-email: Kil0p3 Security Team <security@kil0p3.dev>
License: Proprietary
Project-URL: Homepage, https://github.com/kil0p3-security/kil0p3
Project-URL: Bug Reports, https://github.com/kil0p3-security/kil0p3/issues
Project-URL: Source, https://github.com/kil0p3-security/kil0p3
Project-URL: Documentation, https://kil0p3.dev/docs
Keywords: security,protection,license,drm,anti-piracy,hardware-id,hwid,anti-debugging,code-protection
Classifier: Development Status :: 5 - Production/Stable
Classifier: Intended Audience :: Developers
Classifier: Topic :: Security
Classifier: Topic :: Software Development :: Libraries :: Python Modules
Classifier: License :: Other/Proprietary License
Classifier: Programming Language :: Python :: 3
Classifier: Programming Language :: Python :: 3.8
Classifier: Programming Language :: Python :: 3.9
Classifier: Programming Language :: Python :: 3.10
Classifier: Programming Language :: Python :: 3.11
Classifier: Programming Language :: Python :: 3.12
Classifier: Operating System :: Microsoft :: Windows
Classifier: Operating System :: POSIX :: Linux
Classifier: Operating System :: MacOS
Requires-Python: >=3.8
Requires-Dist: pycryptodome>=3.19.0
Requires-Dist: cryptography>=41.0.0
Requires-Dist: requests>=2.31.0
Requires-Dist: psutil>=5.9.0
Requires-Dist: python-dateutil>=2.8.0
Provides-Extra: dev
Requires-Dist: pytest>=7.0.0; extra == "dev"
Requires-Dist: black>=22.0.0; extra == "dev"
Requires-Dist: isort>=5.0.0; extra == "dev"
Provides-Extra: full
Requires-Dist: colorlog>=6.7.0; extra == "full"
Requires-Dist: pytz>=2023.3; extra == "full"
Dynamic: author
Dynamic: home-page
Dynamic: requires-python
